juno_agent/__init__.py
juno_agent/agent.py
juno_agent/agentic_dependency_resolver.py
juno_agent/config.py
juno_agent/debug_logger.py
juno_agent/editors.py
juno_agent/headless_runner.py
juno_agent/main.py
juno_agent/mcp_cli.py
juno_agent/mcp_config.py
juno_agent/mcp_config_manager.py
juno_agent/scanner.py
juno_agent/simple_ui_tool_callback.py
juno_agent/storage_manager.py
juno_agent/storage_manager_async.py
juno_agent/system_prompt_manager.py
juno_agent/tiny_agent.py
juno_agent/ui.py
juno_agent/utils.py
juno_agent/config/supported_ides.json
juno_agent/fancy_ui/README.md
juno_agent/fancy_ui/__init__.py
juno_agent/fancy_ui/app.py
juno_agent/fancy_ui/app_old.py
juno_agent/fancy_ui/components.py
juno_agent/fancy_ui/models.json
juno_agent/fancy_ui/screens.py
juno_agent/fancy_ui/simple_app.py
juno_agent/fancy_ui/callbacks/__init__.py
juno_agent/fancy_ui/callbacks/textual_tool_callback.py
juno_agent/fancy_ui/handlers/__init__.py
juno_agent/fancy_ui/handlers/app_lifecycle.py
juno_agent/fancy_ui/handlers/chat_handler.py
juno_agent/fancy_ui/handlers/model_handler.py
juno_agent/fancy_ui/handlers/setup_handler.py
juno_agent/fancy_ui/setup/MCP_INSTALLER_README.md
juno_agent/fancy_ui/setup/__init__.py
juno_agent/fancy_ui/setup/agentic_dependency_resolver.py
juno_agent/fancy_ui/setup/api_key_manager.py
juno_agent/fancy_ui/setup/backend_dependency_docs_api.py
juno_agent/fancy_ui/setup/claude_permissions.py
juno_agent/fancy_ui/setup/conftest.py
juno_agent/fancy_ui/setup/dependency_common.py
juno_agent/fancy_ui/setup/dependency_scanner.py
juno_agent/fancy_ui/setup/editor_selector.py
juno_agent/fancy_ui/setup/external_context_manager.py
juno_agent/fancy_ui/setup/mcp_installer.py
juno_agent/fancy_ui/setup/setup_verification_service.py
juno_agent/fancy_ui/styles/chat.tcss
juno_agent/fancy_ui/utils/README.md
juno_agent/fancy_ui/utils/__init__.py
juno_agent/fancy_ui/utils/command_history.py
juno_agent/fancy_ui/utils/message_formatter.py
juno_agent/fancy_ui/utils/subagent_tracker.py
juno_agent-0.2.0.dist-info/METADATA
juno_agent-0.2.0.dist-info/WHEEL
juno_agent-0.2.0.dist-info/entry_points.txt
juno_agent-0.2.0.dist-info/top_level.txt
juno_agent-0.2.0.dist-info/RECORD
