Metadata-Version: 2.4
Name: juno-agent
Version: 0.2.0
Summary: AI-powered coding assistant for developers
Author-email: Juno AI <support@askbudi.ai>
Project-URL: Homepage, https://askbudi.ai
Project-URL: Repository, https://github.com/AskDevAI/juno-agent
Project-URL: Documentation, https://askbudi.ai
Classifier: Development Status :: 3 - Alpha
Classifier: Intended Audience :: Developers
Classifier: License :: OSI Approved :: GNU Affero General Public License v3
Classifier: Programming Language :: Python :: 3
Classifier: Programming Language :: Python :: 3.10
Classifier: Programming Language :: Python :: 3.11
Classifier: Programming Language :: Python :: 3.12
Requires-Python: >=3.10
Requires-Dist: typer[all]>=0.12.0
Requires-Dist: rich>=13.0.0
Requires-Dist: textual>=0.70.0
Requires-Dist: prompt_toolkit>=3.0.52
Requires-Dist: requests>=2.31.0
Requires-Dist: httpx>=0.27.0
Requires-Dist: pydantic>=2.0.0
Requires-Dist: gitpython>=3.1.0
Requires-Dist: toml>=0.10.0
Requires-Dist: click>=8.0.0
Requires-Dist: tinyagent-py[all]>=0.1.18
Requires-Dist: aiosqlite>=0.21.0
Provides-Extra: dev
Requires-Dist: pytest>=7.0.0; extra == "dev"
Requires-Dist: pytest-asyncio>=0.21.0; extra == "dev"
Requires-Dist: pytest-mock>=3.10.0; extra == "dev"
Requires-Dist: black>=23.0.0; extra == "dev"
Requires-Dist: ruff>=0.1.0; extra == "dev"
Requires-Dist: mypy>=1.0.0; extra == "dev"
Requires-Dist: pre-commit>=3.0.0; extra == "dev"
Requires-Dist: textual-dev>=1.0.0; extra == "dev"
Provides-Extra: tracing
Requires-Dist: arize-phoenix>=4.0.0; extra == "tracing"
Requires-Dist: openinference-instrumentation-litellm>=0.1.0; extra == "tracing"
Provides-Extra: clipboard
Requires-Dist: pyperclip>=1.8.0; extra == "clipboard"
